moadian_sdk/__init__.py
moadian_sdk/client.py
moadian_sdk/crypto.py
moadian_sdk/exceptions.py
moadian_sdk/invoice.py
moadian_sdk/models.py
moadian_sdk/utils.py
moadian_sdk-0.2.0.dist-info/licenses/LICENSE
moadian_sdk-0.2.0.dist-info/METADATA
moadian_sdk-0.2.0.dist-info/WHEEL
moadian_sdk-0.2.0.dist-info/top_level.txt
moadian_sdk-0.2.0.dist-info/RECORD
