Metadata-Version: 2.4
Name: moadian-sdk
Version: 0.2.0
Summary: A clean and simple Python SDK for interacting with the Iranian Tax Organization's Moadian API
Author-email: Ali Hatami <alihtt@gmail.com>
License: MIT
Project-URL: Homepage, https://github.com/alihtt/moadian-sdk
Project-URL: Documentation, https://github.com/alihtt/moadian-sdk#readme
Project-URL: Issues, https://github.com/alihtt/moadian-sdk/issues
Project-URL: Repository, https://github.com/alihtt/moadian-sdk
Keywords: moadian,tax,iran,invoice,api,sdk
Classifier: Development Status :: 4 - Beta
Classifier: Intended Audience :: Developers
Classifier: License :: OSI Approved :: MIT License
Classifier: Operating System :: OS Independent
Classifier: Programming Language :: Python :: 3
Classifier: Programming Language :: Python :: 3.9
Classifier: Programming Language :: Python :: 3.10
Classifier: Programming Language :: Python :: 3.11
Classifier: Programming Language :: Python :: 3.12
Classifier: Programming Language :: Python :: 3.13
Classifier: Topic :: Software Development :: Libraries :: Python Modules
Classifier: Topic :: Office/Business :: Financial :: Accounting
Requires-Python: >=3.9
License-File: LICENSE
Requires-Dist: build>=1.3.0
Requires-Dist: cryptography>=46.0.3
Requires-Dist: requests>=2.32.5
Requires-Dist: twine>=6.2.0
Provides-Extra: dev
Requires-Dist: pytest>=7.0.0; extra == "dev"
Requires-Dist: pytest-cov>=4.0.0; extra == "dev"
Dynamic: license-file
